{"info":{"name":"REST Docs to Postman","schema":"https://schema.getpostman.com/json/collection/v2.1.0/collection.json"},"item":[{"name":"generated-snippets","item":[{"name":"api","request":{"method":"POST","header":[{"key":"Content-Type","value":"application/json; charset=UTF-8"}],"body":{"mode":"raw","raw":"{\"id\":null,\"cpf\":\"581.189.150-42\",\"nome\":\"Tadeu\",\"dataNascimento\":\"1899-01-30\",\"idade\":121}"},"url":{"raw":"http://localhost:8080/api","host":["http://localhost:8080"],"path":["","api"]}}}]}]}